{
    "0": "Golden fish with vibrant blue dots.",
    "1": "Junco bird perched on a snow-covered branch.",
    "2": "Chesapeake Bay Retriever surrounded by blooming flowers in a garden.",
    "3": "Plastic bag filled with trash.",
    "4": "Lego-built kite.",
    "5": "a pile of shiny coins.",
    "6": "A vase adorned with floral patterns.",
    "7": "abacus made of wood.",
    "8": "Rice in a bowl",
    "9": "Flowers are hanging on the branch.",
    "10": "A bird in the heavy rain.",
    "11": "An owl on a snowy day.",
    "12": "Melted.",
    "13": "A damselfly in the heavy rain.",
    "14": "melted broccoli.",
    "15": "Guacamole, Sausage, and Potato chips.",
    "16": "A cardoon by the pond.",
    "17": "A dog is wearing clothes.",
    "18": "A monastery by the pond.",
    "19": "A drawing of a spindle.",
    "20": "A strainer filled with colorful dots.",
    "21": "A ladle with fire.",
    "22": "A jay on a snowy day.",
    "23": "An old radio with a spider web.",
    "24": "A glass vase with a dot pattern.",
    "25": "A necklace made of shells.",
    "26": "A sunflower-shaped racket.",
    "27": "A packet on the sand.",
    "28": "A pick on the sand.",
    "29": "A bird with colorful spots.",
    "30": "soap dispenser with a dot pattern.",
    "31": "A wooden ship by the pool.",
    "32": "Foxes playing in the snow.",
    "33": "The limpkin swims in the swamp.",
    "34": "A dog walks through thick mud in a foggy field",
    "35": "A bird on the mountain.",
    "36": "Lego-built bird.",
    "37": "A dog is wearing clothes.",
    "38": "A dog is wearing clothes.",
    "39": "A white stork standing in a shallow wetland.",
    "40": "Bees eat the food.",
    "41": "White ceramic bowl filled with noodles",
    "42": "A blue ceramic bowl filled with a salad",
    "43": "A photo of a parrot",
    "44": "An Ivy wall",
    "45": "A horse",
    "46": "A watermelon",
    "47": "A branch with a withering flower.",
    "48": "A parrot",
    "49": "Noodle served in a white bowl",
    "50": "A horse",
    "51": "A movie poster with a meerkat in a rain",
    "52": "Two cups of icecream",
    "53": "A brown cat sitting on a dead tree",
    "54": "A waterbird",
    "55": "Two vases with flower patterns",
    "56": "Parrots on a branch",
    "57": "A snail shell",
    "58": "Ceramic cups with differnt patterns",
    "59": "A dog on the water",
    "60": "Shorts with star patterns",
    "61": "A plane on the ocean",
    "62": "New car",
    "63": "A dog holding a sword",
    "64": "A dog sitting on a blue couch",
    "65": "Snow-covered Stonehenge",
    "66": "Black-spotted butterfly",
    "67": "A cat sniffing",
    "68": "A goled toad",
    "69": "A coral reef",
    "70": "Fried rice served in a white bowl",
    "71": "A yellow handkerchief",
    "72": "A clutch decorated with diamonds",
    "73": "An eagle on a snowy day.",
    "74": "bitten acorn squash",
    "75": "Ruffed lemur wearing glasses.",
    "76": "A spider on a web.",
    "77": "An wolf on the snowy day.",
    "78": "A dog reading a book.",
    "79": "A Lego-built spider."
}